MANIFEST.in
README.md
setup.cfg
setup.py
toolbox.py
PerceptionToolkit/ColorPalettes.py
PerceptionToolkit/CommandProcessor.py
PerceptionToolkit/DataModel.py
PerceptionToolkit/EventdetectionHelpers.py
PerceptionToolkit/EyeMovementTypes.py
PerceptionToolkit/EyeMovements.py
PerceptionToolkit/PEPluginManager.py
PerceptionToolkit/PluginInterfaces.py
PerceptionToolkit/Version.py
PerceptionToolkit/__init__.py
PerceptionToolkit/plugins/ClassificationEvolutionaryPattern.py
PerceptionToolkit/plugins/ClassificationEvolutionaryPattern.toolbox-plugin
PerceptionToolkit/plugins/ClassificationHMM.py
PerceptionToolkit/plugins/ClassificationHMM.toolbox-plugin
PerceptionToolkit/plugins/ClassificationNeedlemanWunsch.py
PerceptionToolkit/plugins/ClassificationNeedlemanWunsch.toolbox-plugin
PerceptionToolkit/plugins/ClassificationSubsMatch2.py
PerceptionToolkit/plugins/ClassificationSubsMatch2.toolbox-plugin
PerceptionToolkit/plugins/EventdetectionBlink.py
PerceptionToolkit/plugins/EventdetectionBlink.toolbox-plugin
PerceptionToolkit/plugins/EventdetectionEngelbert.py
PerceptionToolkit/plugins/EventdetectionEngelbert.toolbox-plugin
PerceptionToolkit/plugins/EventdetectionIDT.py
PerceptionToolkit/plugins/EventdetectionIDT.toolbox-plugin
PerceptionToolkit/plugins/EventdetectionIHMM.py
PerceptionToolkit/plugins/EventdetectionIHMM.toolbox-plugin
PerceptionToolkit/plugins/EventdetectionIKF.py
PerceptionToolkit/plugins/EventdetectionIKF.toolbox-plugin
PerceptionToolkit/plugins/EventdetectionIMST.py
PerceptionToolkit/plugins/EventdetectionIMST.toolbox-plugin
PerceptionToolkit/plugins/EventdetectionIVT.py
PerceptionToolkit/plugins/EventdetectionIVT.toolbox-plugin
PerceptionToolkit/plugins/MetricFixation.py
PerceptionToolkit/plugins/MetricFixation.toolbox-plugin
PerceptionToolkit/plugins/MetricSaccade.py
PerceptionToolkit/plugins/MetricSaccade.toolbox-plugin
PerceptionToolkit/plugins/PersistenceCSV.py
PerceptionToolkit/plugins/PersistenceCSV.toolbox-plugin
Perception_Engineers_Toolbox.egg-info/PKG-INFO
Perception_Engineers_Toolbox.egg-info/SOURCES.txt
Perception_Engineers_Toolbox.egg-info/dependency_links.txt
Perception_Engineers_Toolbox.egg-info/requires.txt
Perception_Engineers_Toolbox.egg-info/top_level.txt
